ipyida/__init__.py
ipyida/ida_plugin.py
ipyida/ida_qtconsole.py
ipyida/ipyida_plugin_stub.py
ipyida/kernel.py
ipyida/notebook.py
ipyida-2.3.dist-info/licenses/LICENSE
ipyida-2.3.dist-info/METADATA
ipyida-2.3.dist-info/WHEEL
ipyida-2.3.dist-info/top_level.txt
ipyida-2.3.dist-info/RECORD
